climate_categories/__init__.py
climate_categories/_categories.py
climate_categories/_conversions.py
climate_categories/py.typed
climate_categories/search.py
climate_categories/data/BURDI.py
climate_categories/data/BURDI.yaml
climate_categories/data/BURDI_class.py
climate_categories/data/BURDI_class.yaml
climate_categories/data/CRF1999.py
climate_categories/data/CRF1999.yaml
climate_categories/data/CRF2013.py
climate_categories/data/CRF2013.yaml
climate_categories/data/CRF2013_2021.py
climate_categories/data/CRF2013_2021.yaml
climate_categories/data/CRF2013_2022.py
climate_categories/data/CRF2013_2022.yaml
climate_categories/data/CRF2013_2023.py
climate_categories/data/CRF2013_2023.yaml
climate_categories/data/CRFDI.py
climate_categories/data/CRFDI.yaml
climate_categories/data/CRFDI_class.py
climate_categories/data/CRFDI_class.yaml
climate_categories/data/GCB.py
climate_categories/data/GCB.yaml
climate_categories/data/IPCC1996.py
climate_categories/data/IPCC1996.yaml
climate_categories/data/IPCC2006.py
climate_categories/data/IPCC2006.yaml
climate_categories/data/IPCC2006_PRIMAP.py
climate_categories/data/IPCC2006_PRIMAP.yaml
climate_categories/data/ISO3.py
climate_categories/data/ISO3.yaml
climate_categories/data/ISO3_GCAM.py
climate_categories/data/ISO3_GCAM.yaml
climate_categories/data/RCMIP.py
climate_categories/data/RCMIP.yaml
climate_categories/data/__init__.py
climate_categories/data/conversion.IPCC1996.IPCC2006.csv
climate_categories/data/gas.py
climate_categories/data/gas.yaml
climate_categories/tests/__init__.py
climate_categories/tests/conftest.py
climate_categories/tests/examples.py
climate_categories/tests/test_climate_categories.py
climate_categories/tests/test_conversions.py
climate_categories/tests/test_crf.py
climate_categories/tests/test_di.py
climate_categories/tests/test_gas.py
climate_categories/tests/test_ipcc.py
climate_categories/tests/test_iso3.py
climate_categories/tests/test_overcounting.py
climate_categories/tests/test_primap.py
climate_categories-10.0.4.dist-info/LICENSE
climate_categories-10.0.4.dist-info/METADATA
climate_categories-10.0.4.dist-info/WHEEL
climate_categories-10.0.4.dist-info/top_level.txt
climate_categories-10.0.4.dist-info/RECORD
