Metadata-Version: 2.2
Name: climate_categories
Version: 10.0.4
Summary: Commonly used codes, categories, terminologies, and nomenclatures used in climate policy analysis as a Python package.
Home-page: https://github.com/primap-community/climate_categories
Author: Mika Pflüger
Author-email: mika.pflueger@climate-resource.com
License: Apache Software License 2.0
Project-URL: Documentation, https://climate-categories.readthedocs.io/
Classifier: Development Status :: 4 - Beta
Classifier: Intended Audience :: Science/Research
Classifier: Topic :: Scientific/Engineering :: Atmospheric Science
Classifier: License :: OSI Approved :: Apache Software License
Classifier: Natural Language :: English
Classifier: Programming Language :: Python :: 3
Classifier: Programming Language :: Python :: 3.11
Classifier: Programming Language :: Python :: 3.12
Classifier: Programming Language :: Python :: 3.13
Requires-Python: <3.14,>=3.11
License-File: LICENSE
Requires-Dist: networkx>=3
Requires-Dist: pandas>=2
Requires-Dist: pandas>=2.2.3; python_version >= "3.13"
Requires-Dist: strictyaml>=1.6
Requires-Dist: natsort>=8
Requires-Dist: ruamel.yaml>=0.17.2
Requires-Dist: pyparsing>=3.1
Requires-Dist: immutables>=0.20
Requires-Dist: immutables>=0.21; python_version >= "3.13"
Requires-Dist: black>=22.1
Requires-Dist: numpy>=1.26
Requires-Dist: numpy>=2.1.3; python_version >= "3.13"
Provides-Extra: test
Requires-Dist: pytest>=8.3.3; extra == "test"
Requires-Dist: pytest-cov>=5; extra == "test"
Requires-Dist: xdoctest>=1.2; extra == "test"
Provides-Extra: dev
Requires-Dist: pip; extra == "dev"
Requires-Dist: tbump; extra == "dev"
Requires-Dist: wheel; extra == "dev"
Requires-Dist: build; extra == "dev"
Requires-Dist: ruff; extra == "dev"
Requires-Dist: coverage; extra == "dev"
Requires-Dist: Sphinx; extra == "dev"
Requires-Dist: twine; extra == "dev"
Requires-Dist: pytest; extra == "dev"
Requires-Dist: pre-commit; extra == "dev"
Requires-Dist: sphinx_rtd_theme; extra == "dev"
Requires-Dist: ipykernel; extra == "dev"
Requires-Dist: nbsphinx; extra == "dev"
Requires-Dist: networkx; extra == "dev"
Requires-Dist: xdoctest; extra == "dev"
Requires-Dist: tox; extra == "dev"
Requires-Dist: tox-uv>=1.11.3; extra == "dev"
Requires-Dist: unfccc_di_api>=3.0.1; extra == "dev"
Requires-Dist: openscm-units; extra == "dev"
Requires-Dist: pycountry; extra == "dev"
Requires-Dist: lxml; extra == "dev"
Requires-Dist: tqdm; extra == "dev"
Requires-Dist: pypdf-table-extraction; extra == "dev"
Requires-Dist: numpy<2; extra == "dev"
